milvus_lite/__init__.py
milvus_lite/cmdline.py
milvus_lite/server.py
milvus_lite/server_manager.py
milvus_lite/lib/libdouble-conversion.so.3
milvus_lite/lib/libgcc_s.so.1
milvus_lite/lib/libgflags_nothreads.so.2.2
milvus_lite/lib/libgfortran.so.5
milvus_lite/lib/libglog.so.1
milvus_lite/lib/libgomp.so.1
milvus_lite/lib/libknowhere.so
milvus_lite/lib/libm.so.6
milvus_lite/lib/libopenblas.so.0
milvus_lite/lib/libquadmath.so.0
milvus_lite/lib/libtbb.so.12
milvus_lite/lib/libz.so.1
milvus_lite/lib/milvus
milvus_lite-2.5.0.dist-info/METADATA
milvus_lite-2.5.0.dist-info/WHEEL
milvus_lite-2.5.0.dist-info/entry_points.txt
milvus_lite-2.5.0.dist-info/top_level.txt
milvus_lite-2.5.0.dist-info/RECORD
