Metadata-Version: 2.1
Name: milvus-lite
Version: 2.5.0
Summary: A lightweight version of Milvus wrapped with Python.
Home-page: https://github.com/milvus-io/milvus-lite.git
Author: Milvus Team
Author-email: milvus-team@zilliz.com
Requires-Python: >=3.7
Requires-Dist: tqdm
